odoo10_addon_website_sale_price_tier-10.0.1.1.1-nspkg.pth
odoo/addons/website_sale_price_tier/README.rst
odoo/addons/website_sale_price_tier/__init__.py
odoo/addons/website_sale_price_tier/__manifest__.py
odoo/addons/website_sale_price_tier/demo/account_tax.xml
odoo/addons/website_sale_price_tier/demo/product_pricelist_item.xml
odoo/addons/website_sale_price_tier/demo/product_product.xml
odoo/addons/website_sale_price_tier/i18n/ar.po
odoo/addons/website_sale_price_tier/i18n/bg.po
odoo/addons/website_sale_price_tier/i18n/bs.po
odoo/addons/website_sale_price_tier/i18n/ca.po
odoo/addons/website_sale_price_tier/i18n/cs.po
odoo/addons/website_sale_price_tier/i18n/da.po
odoo/addons/website_sale_price_tier/i18n/de.po
odoo/addons/website_sale_price_tier/i18n/el_GR.po
odoo/addons/website_sale_price_tier/i18n/en_GB.po
odoo/addons/website_sale_price_tier/i18n/es.po
odoo/addons/website_sale_price_tier/i18n/es_AR.po
odoo/addons/website_sale_price_tier/i18n/es_CL.po
odoo/addons/website_sale_price_tier/i18n/es_CO.po
odoo/addons/website_sale_price_tier/i18n/es_CR.po
odoo/addons/website_sale_price_tier/i18n/es_DO.po
odoo/addons/website_sale_price_tier/i18n/es_EC.po
odoo/addons/website_sale_price_tier/i18n/es_MX.po
odoo/addons/website_sale_price_tier/i18n/es_PE.po
odoo/addons/website_sale_price_tier/i18n/et.po
odoo/addons/website_sale_price_tier/i18n/eu.po
odoo/addons/website_sale_price_tier/i18n/fa.po
odoo/addons/website_sale_price_tier/i18n/fi.po
odoo/addons/website_sale_price_tier/i18n/fr.po
odoo/addons/website_sale_price_tier/i18n/fr_CH.po
odoo/addons/website_sale_price_tier/i18n/gl.po
odoo/addons/website_sale_price_tier/i18n/he.po
odoo/addons/website_sale_price_tier/i18n/hr.po
odoo/addons/website_sale_price_tier/i18n/hr_HR.po
odoo/addons/website_sale_price_tier/i18n/hu.po
odoo/addons/website_sale_price_tier/i18n/id.po
odoo/addons/website_sale_price_tier/i18n/it.po
odoo/addons/website_sale_price_tier/i18n/ja.po
odoo/addons/website_sale_price_tier/i18n/ko.po
odoo10_addon_website_sale_price_tier-10.0.1.1.1.dist-info/METADATA
odoo10_addon_website_sale_price_tier-10.0.1.1.1.dist-info/WHEEL
odoo10_addon_website_sale_price_tier-10.0.1.1.1.dist-info/namespace_packages.txt
odoo10_addon_website_sale_price_tier-10.0.1.1.1.dist-info/top_level.txt
odoo10_addon_website_sale_price_tier-10.0.1.1.1.dist-info/RECORD
